odoo/addons/maintenance_remote/README.rst
odoo/addons/maintenance_remote/__init__.py
odoo/addons/maintenance_remote/__manifest__.py
odoo/addons/maintenance_remote/i18n/es.po
odoo/addons/maintenance_remote/i18n/fr.po
odoo/addons/maintenance_remote/i18n/it.po
odoo/addons/maintenance_remote/i18n/maintenance_remote.pot
odoo/addons/maintenance_remote/i18n/pt_BR.po
odoo/addons/maintenance_remote/models/__init__.py
odoo/addons/maintenance_remote/models/maintenance_request.py
odoo/addons/maintenance_remote/readme/CONTRIBUTORS.rst
odoo/addons/maintenance_remote/readme/DESCRIPTION.rst
odoo/addons/maintenance_remote/static/description/icon.png
odoo/addons/maintenance_remote/static/description/index.html
odoo/addons/maintenance_remote/views/maintenance_request.xml
odoo14_addon_maintenance_remote-14.0.1.0.1.dev8.dist-info/METADATA
odoo14_addon_maintenance_remote-14.0.1.0.1.dev8.dist-info/WHEEL
odoo14_addon_maintenance_remote-14.0.1.0.1.dev8.dist-info/top_level.txt
odoo14_addon_maintenance_remote-14.0.1.0.1.dev8.dist-info/RECORD
